is_numeric/__init__.py
is_numeric/numerical.py
is_numeric/version.py
better_is_numeric-2.0.1.dist-info/METADATA
better_is_numeric-2.0.1.dist-info/WHEEL
better_is_numeric-2.0.1.dist-info/top_level.txt
better_is_numeric-2.0.1.dist-info/RECORD
