Metadata-Version: 2.4
Name: better-is-numeric
Version: 2.0.1
Summary: An enhancement of str.isnumeric()
Home-page: https://codeberg.org/Butter/numerical
Author: LiterallyButter
Classifier: Programming Language :: Python :: 3.9
Classifier: License :: OSI Approved :: The Unlicense (Unlicense)
Classifier: Intended Audience :: Developers
Classifier: Topic :: Software Development
Classifier: Topic :: Software Development :: Libraries
Classifier: Topic :: Software Development :: Libraries :: Python Modules
Dynamic: author
Dynamic: classifier
Dynamic: description
Dynamic: description-content-type
Dynamic: home-page
Dynamic: summary
